dash_tree_components/Tree.py
dash_tree_components/__init__.py
dash_tree_components/_imports_.py
dash_tree_components/dash_tree_components.min.js
dash_tree_components/dash_tree_components.min.js.map
dash_tree_components/metadata.json
dash_tree_components/package-info.json
dash_tree_components-0.0.8.dist-info/LICENSE
dash_tree_components-0.0.8.dist-info/METADATA
dash_tree_components-0.0.8.dist-info/WHEEL
dash_tree_components-0.0.8.dist-info/top_level.txt
dash_tree_components-0.0.8.dist-info/RECORD
