Metadata-Version: 2.1
Name: dash_tree_components
Version: 0.0.8
Summary: Tree components for Dash
Author: Wouter Wakker <wouter.wakker@outlook.com>
License: MIT
Classifier: Framework :: Dash
License-File: LICENSE
